occupiedgpus/__init__.py
occupiedgpus/core.py
occupiedgpus-0.0.8.dist-info/LICENSE
occupiedgpus-0.0.8.dist-info/METADATA
occupiedgpus-0.0.8.dist-info/WHEEL
occupiedgpus-0.0.8.dist-info/top_level.txt
occupiedgpus-0.0.8.dist-info/RECORD
