Metadata-Version: 2.1
Name: occupiedgpus
Version: 0.0.8
Summary: The program for occupation of GPUs.
Home-page: https://github.com/jinzcdev/occupied-gpus.git
Author: Zhichao Jin
Author-email: jinzcdev@icloud.com
License: UNKNOWN
Platform: UNKNOWN
Classifier: Programming Language :: Python :: 3
Classifier: License :: OSI Approved :: MIT License
Classifier: Operating System :: OS Independent
License-File: LICENSE
Requires-Dist: torch
Requires-Dist: nvidia-ml-py
